myfds_package/__init__.py
myfds_package/somecode.py
myfds_package-0.8.dist-info/METADATA
myfds_package-0.8.dist-info/WHEEL
myfds_package-0.8.dist-info/top_level.txt
myfds_package-0.8.dist-info/RECORD
