Metadata-Version: 2.1
Name: myfds-package
Version: 0.8
Summary: My first package
Home-page: https://github.com/Ditmarscehen/myfds_package
License: UNKNOWN
Platform: UNKNOWN
Requires-Dist: scipy
Requires-Dist: numpy (<=1.20.0)
